physioprep/__init__.py
physioprep/mimic_iii_ms_tk/__init__.py
physioprep/mimic_iii_ms_tk/data/preset.pkl.gz
physioprep/mimic_iii_ms_tk/module.py
physioprep/mimic_iii_ms_tk/utility.py
physioprep/mimic_iii_ms_tk/validation.py
physioprep-0.0.2.dist-info/METADATA
physioprep-0.0.2.dist-info/WHEEL
physioprep-0.0.2.dist-info/licenses/LICENSE
physioprep-0.0.2.dist-info/RECORD
