Metadata-Version: 2.4
Name: physioprep
Version: 0.0.2
Summary: 
License-File: LICENSE
Author: Your Name
Author-email: you@example.com
Requires-Python: >=3.10,<4.0
Classifier: Programming Language :: Python :: 3
Classifier: Programming Language :: Python :: 3.10
Classifier: Programming Language :: Python :: 3.11
Classifier: Programming Language :: Python :: 3.12
Classifier: Programming Language :: Python :: 3.13
Classifier: Programming Language :: Python :: 3.14
Requires-Dist: jupyter (>=1.1.1,<2.0.0)
Requires-Dist: numpy (<2.0)
Requires-Dist: pandas (>=2.3.2,<3.0.0)
Requires-Dist: pooch (>=1.8.2,<2.0.0)
Requires-Dist: requests (>=2.32.5,<3.0.0)
Requires-Dist: tqdm (>=4.67.1,<5.0.0)
Requires-Dist: wfdb (>=4.3.0,<5.0.0)
